fluxcrud/__init__.py
fluxcrud/_version.py
fluxcrud/flux.py
fluxcrud/py.typed
fluxcrud/async_patterns/__init__.py
fluxcrud/async_patterns/concurrency.py
fluxcrud/async_patterns/dataloader.py
fluxcrud/cache/__init__.py
fluxcrud/cache/backends.py
fluxcrud/cache/manager.py
fluxcrud/core/__init__.py
fluxcrud/core/base.py
fluxcrud/core/exceptions.py
fluxcrud/core/repository.py
fluxcrud/database/__init__.py
fluxcrud/database/drivers.py
fluxcrud/operations/__init__.py
fluxcrud/operations/create.py
fluxcrud/operations/delete.py
fluxcrud/operations/list.py
fluxcrud/operations/read.py
fluxcrud/operations/update.py
fluxcrud/query/__init__.py
fluxcrud/query/builder.py
fluxcrud/query/optimizer.py
fluxcrud/transactions/__init__.py
fluxcrud/transactions/manager.py
fluxcrud/types/__init__.py
fluxcrud/types/protocols.py
fluxcrud/web/__init__.py
fluxcrud/web/deps.py
fluxcrud/web/middleware.py
fluxcrud/web/router.py
fluxcrud/web/websockets.py
fluxcrud-0.1.1.dist-info/METADATA
fluxcrud-0.1.1.dist-info/WHEEL
fluxcrud-0.1.1.dist-info/licenses/LICENSE
fluxcrud-0.1.1.dist-info/RECORD
